python_ccb/__init__.py
python_ccb-1.0.1.dist-info/WHEEL
python_ccb-1.0.1.dist-info/METADATA
python_ccb-1.0.1.dist-info/RECORD
