Metadata-Version: 2.1
Name: python-ccb
Version: 1.0.1
Summary: Python wrapper for clearcheckbook
Home-page: https://sr.ht/~ocurero/python-ccb/
License: Apache 2.0
Keywords: clearcheckbook,api,rest,wrapper
Author: Oscar Curero
Author-email: oscar@curero.es
Requires-Python: >=3.6,<4.0
Classifier: Development Status :: 5 - Production/Stable
Classifier: Intended Audience :: Developers
Classifier: License :: OSI Approved :: Apache Software License
Classifier: License :: Other/Proprietary License
Classifier: Programming Language :: Python :: 3
Classifier: Programming Language :: Python :: 3.10
Classifier: Programming Language :: Python :: 3.6
Classifier: Programming Language :: Python :: 3.7
Classifier: Programming Language :: Python :: 3.8
Classifier: Programming Language :: Python :: 3.9
Classifier: Topic :: Software Development :: Libraries
Requires-Dist: attrs
Requires-Dist: pendulum
Requires-Dist: requests
Project-URL: Documentation, https://python-ccb.readthedocs.io/
Project-URL: Repository, https://hg.sr.ht/~ocurero/python-ccb
